esgf_qa/__init__.py
esgf_qa/_constants.py
esgf_qa/_version.py
esgf_qa/cluster_results.py
esgf_qa/con_checks.py
esgf_qa/qaviewer.py
esgf_qa/run_qa.py
esgf_qa-0.4.0.dist-info/licenses/LICENSE
tests/test_cli.py
tests/test_cluster_results.py
tests/test_con_checks.py
tests/test_qaviewer.py
tests/test_run_dummy_qa.py
tests/test_run_qa.py
esgf_qa-0.4.0.dist-info/METADATA
esgf_qa-0.4.0.dist-info/WHEEL
esgf_qa-0.4.0.dist-info/entry_points.txt
esgf_qa-0.4.0.dist-info/top_level.txt
esgf_qa-0.4.0.dist-info/RECORD
