Metadata-Version: 2.4
Name: esgf-qa
Version: 0.4.0
Summary: QA based on compliance-checker
Author-email: Martin Schupfner <schupfner@dkrz.de>
Maintainer-email: Martin Schupfner <schupfner@dkrz.de>
License-Expression: Apache-2.0
Project-URL: homepage, https://github.com/ESGF/esgf-qa
Project-URL: repository, https://github.com/ESGF/esgf-qa
Keywords: compliance checker,plugin,wcrp,cmip,cmip6,cmip7,cordex,cordex-cmip6,qc,qa,quality control,quality assurance,esgf
Classifier: Programming Language :: Python :: 3 :: Only
Classifier: Programming Language :: Python :: 3.10
Classifier: Programming Language :: Python :: 3.11
Classifier: Programming Language :: Python :: 3.12
Classifier: Programming Language :: Python :: 3.13
Requires-Python: >=3.10
License-File: LICENSE
Requires-Dist: cftime
Requires-Dist: cf_xarray
Requires-Dist: compliance-checker>=5.3.0
Requires-Dist: dask
Requires-Dist: netCDF4
Requires-Dist: pandas
Requires-Dist: textual
Requires-Dist: xarray
Requires-Dist: cc-plugin-cc6>=0.4.0
Requires-Dist: cc-plugin-wcrp
Provides-Extra: dev
Requires-Dist: black; extra == "dev"
Requires-Dist: build; extra == "dev"
Requires-Dist: isort; extra == "dev"
Requires-Dist: flake8; extra == "dev"
Requires-Dist: flake8-builtins; extra == "dev"
Requires-Dist: flake8-comprehensions; extra == "dev"
Requires-Dist: flake8-mutable; extra == "dev"
Requires-Dist: flake8-print; extra == "dev"
Requires-Dist: pre-commit; extra == "dev"
Requires-Dist: pytest>=7.0.0; extra == "dev"
Requires-Dist: pytest-flake8; extra == "dev"
Requires-Dist: pytest-asyncio; extra == "dev"
Requires-Dist: ruff>=0.1.0; extra == "dev"
Requires-Dist: twine; extra == "dev"
Requires-Dist: wheel; extra == "dev"
Dynamic: license-file
